gurufocus_api/__init__.py
gurufocus_api/client.py
gurufocus_api/config.py
gurufocus_api/exceptions.py
gurufocus_api/logging.py
gurufocus_api/py.typed
gurufocus_api/rate_limiter.py
gurufocus_api/usage_tracker.py
gurufocus_api/analysis/__init__.py
gurufocus_api/cache/__init__.py
gurufocus_api/cache/base.py
gurufocus_api/cache/config.py
gurufocus_api/cache/disk.py
gurufocus_api/cache/manager.py
gurufocus_api/endpoints/__init__.py
gurufocus_api/endpoints/economic.py
gurufocus_api/endpoints/etfs.py
gurufocus_api/endpoints/gurus.py
gurufocus_api/endpoints/insiders.py
gurufocus_api/endpoints/personal.py
gurufocus_api/endpoints/politicians.py
gurufocus_api/endpoints/reference.py
gurufocus_api/endpoints/stocks.py
gurufocus_api/models/__init__.py
gurufocus_api/models/dividends.py
gurufocus_api/models/economic.py
gurufocus_api/models/estimate_history.py
gurufocus_api/models/estimates.py
gurufocus_api/models/etf.py
gurufocus_api/models/executives.py
gurufocus_api/models/financials.py
gurufocus_api/models/gurus.py
gurufocus_api/models/indicators.py
gurufocus_api/models/insider_updates.py
gurufocus_api/models/insiders.py
gurufocus_api/models/keyratios.py
gurufocus_api/models/news.py
gurufocus_api/models/ohlc.py
gurufocus_api/models/operating.py
gurufocus_api/models/ownership.py
gurufocus_api/models/personal.py
gurufocus_api/models/politicians.py
gurufocus_api/models/price.py
gurufocus_api/models/quote.py
gurufocus_api/models/reference.py
gurufocus_api/models/screener.py
gurufocus_api/models/summary.py
gurufocus_api/models/trades_history.py
gurufocus_api-0.6.0.dist-info/METADATA
gurufocus_api-0.6.0.dist-info/WHEEL
gurufocus_api-0.6.0.dist-info/RECORD
