Metadata-Version: 2.4
Name: gurufocus-api
Version: 0.6.0
Summary: Unofficial Python client library for the GuruFocus API
Project-URL: Homepage, https://github.com/u-daveblack/gurufocus-mcp
Project-URL: Documentation, https://github.com/u-daveblack/gurufocus-mcp#readme
Project-URL: Repository, https://github.com/u-daveblack/gurufocus-mcp
Author: David Black
License-Expression: MIT
Keywords: api,finance,gurufocus,investing,stocks
Classifier: Development Status :: 3 - Alpha
Classifier: Intended Audience :: Developers
Classifier: Intended Audience :: Financial and Insurance Industry
Classifier: License :: OSI Approved :: MIT License
Classifier: Programming Language :: Python :: 3
Classifier: Programming Language :: Python :: 3.11
Classifier: Programming Language :: Python :: 3.12
Classifier: Topic :: Office/Business :: Financial :: Investment
Classifier: Typing :: Typed
Requires-Python: >=3.11
Requires-Dist: diskcache>=5.6
Requires-Dist: httpx>=0.27
Requires-Dist: pydantic-settings>=2.0
Requires-Dist: pydantic>=2.0
Requires-Dist: structlog>=24.0
Provides-Extra: dev
Requires-Dist: mypy>=1.13; extra == 'dev'
Requires-Dist: opentelemetry-api>=1.20; extra == 'dev'
Requires-Dist: opentelemetry-sdk>=1.20; extra == 'dev'
Requires-Dist: pytest-asyncio>=0.24; extra == 'dev'
Requires-Dist: pytest-cov>=5.0; extra == 'dev'
Requires-Dist: pytest>=8.0; extra == 'dev'
Requires-Dist: respx>=0.21; extra == 'dev'
Requires-Dist: ruff>=0.8; extra == 'dev'
Provides-Extra: otel
Requires-Dist: opentelemetry-api>=1.20; extra == 'otel'
Requires-Dist: opentelemetry-sdk>=1.20; extra == 'otel'
